lunr/__init__.py
lunr/builder.py
lunr/exceptions.py
lunr/field_ref.py
lunr/idf.py
lunr/index.py
lunr/lunr.py
lunr/match_data.py
lunr/pipeline.py
lunr/query.py
lunr/query_lexer.py
lunr/query_parser.py
lunr/stemmer.py
lunr/stop_word_filter.py
lunr/token.py
lunr/token_set.py
lunr/token_set_builder.py
lunr/tokenizer.py
lunr/trimmer.py
lunr/utils.py
lunr/vector.py
lunr/languages/__init__.py
lunr/languages/stemmer.py
lunr/languages/trimmer.py
lunr-0.7.0.dist-info/METADATA
lunr-0.7.0.dist-info/WHEEL
lunr-0.7.0.dist-info/licenses/LICENSE
lunr-0.7.0.dist-info/RECORD
